tograml_pydantic_utils/__init__.py
tograml_pydantic_utils/_logger.py
tograml_pydantic_utils/mixins.py
tograml_pydantic_utils/pydantic.py
tograml_pydantic_utils/types.py
tograml_pydantic_utils/update_forward_refs_helper.py
tograml_pydantic_utils-0.3.dist-info/METADATA
tograml_pydantic_utils-0.3.dist-info/WHEEL
tograml_pydantic_utils-0.3.dist-info/licenses/LICENSE
tograml_pydantic_utils-0.3.dist-info/RECORD
